Testsuite: comp207p.target.DynamicVariableFoldingTest
Tests run: 5, Failures: 0, Errors: 5, Skipped: 0, Time elapsed: 0.035 sec

Testcase: testMethodThree took 0.004 sec
	Caused an ERROR
Bad type on operand stack
Exception Details:
  Location:
    comp207p/target/DynamicVariableFolding.methodTwo()Z @13: invokevirtual
  Reason:
    Type integer (current frame, stack[6]) is not assignable to 'java/io/PrintStream'
  Current Frame:
    bci: @13
    flags: { }
    locals: { 'comp207p/target/DynamicVariableFolding' }
    stack: { integer, integer, 'java/io/PrintStream', integer, integer, integer, integer, integer }
  Bytecode:
    0x0000000: 1130 3912 02b2 0003 0403 0404 04b6 0004
    0x0000010: 0304 0304 ac                           

java.lang.VerifyError: Bad type on operand stack
Exception Details:
  Location:
    comp207p/target/DynamicVariableFolding.methodTwo()Z @13: invokevirtual
  Reason:
    Type integer (current frame, stack[6]) is not assignable to 'java/io/PrintStream'
  Current Frame:
    bci: @13
    flags: { }
    locals: { 'comp207p/target/DynamicVariableFolding' }
    stack: { integer, integer, 'java/io/PrintStream', integer, integer, integer, integer, integer }
  Bytecode:
    0x0000000: 1130 3912 02b2 0003 0403 0404 04b6 0004
    0x0000010: 0304 0304 ac                           

	at comp207p.target.DynamicVariableFoldingTest.<init>(Unknown Source)
	at java.lang.reflect.Constructor.newInstance(Constructor.java:408)

Testcase: testMethodFour took 0 sec
	Caused an ERROR
Bad type on operand stack
Exception Details:
  Location:
    comp207p/target/DynamicVariableFolding.methodTwo()Z @13: invokevirtual
  Reason:
    Type integer (current frame, stack[6]) is not assignable to 'java/io/PrintStream'
  Current Frame:
    bci: @13
    flags: { }
    locals: { 'comp207p/target/DynamicVariableFolding' }
    stack: { integer, integer, 'java/io/PrintStream', integer, integer, integer, integer, integer }
  Bytecode:
    0x0000000: 1130 3912 02b2 0003 0403 0404 04b6 0004
    0x0000010: 0304 0304 ac                           

java.lang.VerifyError: Bad type on operand stack
Exception Details:
  Location:
    comp207p/target/DynamicVariableFolding.methodTwo()Z @13: invokevirtual
  Reason:
    Type integer (current frame, stack[6]) is not assignable to 'java/io/PrintStream'
  Current Frame:
    bci: @13
    flags: { }
    locals: { 'comp207p/target/DynamicVariableFolding' }
    stack: { integer, integer, 'java/io/PrintStream', integer, integer, integer, integer, integer }
  Bytecode:
    0x0000000: 1130 3912 02b2 0003 0403 0404 04b6 0004
    0x0000010: 0304 0304 ac                           

	at comp207p.target.DynamicVariableFoldingTest.<init>(Unknown Source)
	at java.lang.reflect.Constructor.newInstance(Constructor.java:408)

Testcase: testMethodOne took 0.001 sec
	Caused an ERROR
Bad type on operand stack
Exception Details:
  Location:
    comp207p/target/DynamicVariableFolding.methodTwo()Z @13: invokevirtual
  Reason:
    Type integer (current frame, stack[6]) is not assignable to 'java/io/PrintStream'
  Current Frame:
    bci: @13
    flags: { }
    locals: { 'comp207p/target/DynamicVariableFolding' }
    stack: { integer, integer, 'java/io/PrintStream', integer, integer, integer, integer, integer }
  Bytecode:
    0x0000000: 1130 3912 02b2 0003 0403 0404 04b6 0004
    0x0000010: 0304 0304 ac                           

java.lang.VerifyError: Bad type on operand stack
Exception Details:
  Location:
    comp207p/target/DynamicVariableFolding.methodTwo()Z @13: invokevirtual
  Reason:
    Type integer (current frame, stack[6]) is not assignable to 'java/io/PrintStream'
  Current Frame:
    bci: @13
    flags: { }
    locals: { 'comp207p/target/DynamicVariableFolding' }
    stack: { integer, integer, 'java/io/PrintStream', integer, integer, integer, integer, integer }
  Bytecode:
    0x0000000: 1130 3912 02b2 0003 0403 0404 04b6 0004
    0x0000010: 0304 0304 ac                           

	at comp207p.target.DynamicVariableFoldingTest.<init>(Unknown Source)
	at java.lang.reflect.Constructor.newInstance(Constructor.java:408)

Testcase: testMethodTwoReturn took 0 sec
	Caused an ERROR
Bad type on operand stack
Exception Details:
  Location:
    comp207p/target/DynamicVariableFolding.methodTwo()Z @13: invokevirtual
  Reason:
    Type integer (current frame, stack[6]) is not assignable to 'java/io/PrintStream'
  Current Frame:
    bci: @13
    flags: { }
    locals: { 'comp207p/target/DynamicVariableFolding' }
    stack: { integer, integer, 'java/io/PrintStream', integer, integer, integer, integer, integer }
  Bytecode:
    0x0000000: 1130 3912 02b2 0003 0403 0404 04b6 0004
    0x0000010: 0304 0304 ac                           

java.lang.VerifyError: Bad type on operand stack
Exception Details:
  Location:
    comp207p/target/DynamicVariableFolding.methodTwo()Z @13: invokevirtual
  Reason:
    Type integer (current frame, stack[6]) is not assignable to 'java/io/PrintStream'
  Current Frame:
    bci: @13
    flags: { }
    locals: { 'comp207p/target/DynamicVariableFolding' }
    stack: { integer, integer, 'java/io/PrintStream', integer, integer, integer, integer, integer }
  Bytecode:
    0x0000000: 1130 3912 02b2 0003 0403 0404 04b6 0004
    0x0000010: 0304 0304 ac                           

	at comp207p.target.DynamicVariableFoldingTest.<init>(Unknown Source)
	at java.lang.reflect.Constructor.newInstance(Constructor.java:408)

Testcase: testMethodTwoOut took 0 sec
	Caused an ERROR
Bad type on operand stack
Exception Details:
  Location:
    comp207p/target/DynamicVariableFolding.methodTwo()Z @13: invokevirtual
  Reason:
    Type integer (current frame, stack[6]) is not assignable to 'java/io/PrintStream'
  Current Frame:
    bci: @13
    flags: { }
    locals: { 'comp207p/target/DynamicVariableFolding' }
    stack: { integer, integer, 'java/io/PrintStream', integer, integer, integer, integer, integer }
  Bytecode:
    0x0000000: 1130 3912 02b2 0003 0403 0404 04b6 0004
    0x0000010: 0304 0304 ac                           

java.lang.VerifyError: Bad type on operand stack
Exception Details:
  Location:
    comp207p/target/DynamicVariableFolding.methodTwo()Z @13: invokevirtual
  Reason:
    Type integer (current frame, stack[6]) is not assignable to 'java/io/PrintStream'
  Current Frame:
    bci: @13
    flags: { }
    locals: { 'comp207p/target/DynamicVariableFolding' }
    stack: { integer, integer, 'java/io/PrintStream', integer, integer, integer, integer, integer }
  Bytecode:
    0x0000000: 1130 3912 02b2 0003 0403 0404 04b6 0004
    0x0000010: 0304 0304 ac                           

	at comp207p.target.DynamicVariableFoldingTest.<init>(Unknown Source)
	at java.lang.reflect.Constructor.newInstance(Constructor.java:408)

